policyengine_il/__init__.py
policyengine_il/constants.py
policyengine_il/entities.py
policyengine_il/model_api.py
policyengine_il/modelled_policies.yaml
policyengine_il/parameters/gov/README.md
policyengine_il/parameters/gov/low_income_municipal_tax_reduction_rate.yaml
policyengine_il/parameters/simulation/README.md
policyengine_il/parameters/simulation/marginal_tax_rate_adults.yaml
policyengine_il/tests/household_net_income.yaml
policyengine_il/tests/max_low_income_municipal_tax_reduction.yaml
policyengine_il/tests/max_low_income_municipal_tax_reduction_rate.yaml
policyengine_il/variables/age.py
policyengine_il/variables/employment_income.py
policyengine_il/variables/gross_income.py
policyengine_il/variables/household_benefits.py
policyengine_il/variables/household_market_income.py
policyengine_il/variables/household_net_income.py
policyengine_il/variables/household_size.py
policyengine_il/variables/household_tax.py
policyengine_il/variables/is_adult.py
policyengine_il/variables/marginal_tax_rate.py
policyengine_il/variables/market_income.py
policyengine_il/variables/pension_income.py
policyengine_il/variables/self_employment_income.py
policyengine_il/variables/tax.py
policyengine_il/variables/gov/municipal_tax.py
policyengine_il/variables/gov/low_income_municipal_tax_reduction/low_income_municipal_tax_reduction_income.py
policyengine_il/variables/gov/low_income_municipal_tax_reduction/max_low_income_municipal_tax_reduction.py
policyengine_il/variables/gov/low_income_municipal_tax_reduction/max_low_income_municipal_tax_reduction_rate.py
policyengine_il/variables/input/README.md
policyengine_il/variables/input/demographic/README.md
policyengine_il/variables/input/demographic/gender.py
policyengine_il-0.1.0.dist-info/LICENSE
policyengine_il-0.1.0.dist-info/METADATA
policyengine_il-0.1.0.dist-info/WHEEL
policyengine_il-0.1.0.dist-info/entry_points.txt
policyengine_il-0.1.0.dist-info/top_level.txt
policyengine_il-0.1.0.dist-info/RECORD
